agentic_kernel/__init__.py
agentic_kernel/app.py
agentic_kernel/config_types.py
agentic_kernel/exceptions.py
agentic_kernel/task_manager.py
agentic_kernel/types.py
agentic_kernel/agents/README.md
agentic_kernel/agents/__init__.py
agentic_kernel/agents/base.py
agentic_kernel/agents/chat_agent.py
agentic_kernel/agents/coder.py
agentic_kernel/agents/coder_agent.py
agentic_kernel/agents/file_surfer.py
agentic_kernel/agents/file_surfer_agent.py
agentic_kernel/agents/orchestrator_agent.py
agentic_kernel/agents/role_manager.py
agentic_kernel/agents/sandbox.py
agentic_kernel/agents/terminal.py
agentic_kernel/agents/terminal_agent.py
agentic_kernel/agents/web_surfer.py
agentic_kernel/agents/web_surfer_agent.py
agentic_kernel/agents/sandbox/__init__.py
agentic_kernel/agents/sandbox/base.py
agentic_kernel/agents/sandbox/docker_sandbox.py
agentic_kernel/agents/tests/test_role_manager.py
agentic_kernel/communication/README.md
agentic_kernel/communication/__init__.py
agentic_kernel/communication/capability_registry.py
agentic_kernel/communication/collaborative_messages.py
agentic_kernel/communication/collaborative_protocol.py
agentic_kernel/communication/conflict.py
agentic_kernel/communication/consensus.py
agentic_kernel/communication/coordination.py
agentic_kernel/communication/dynamic_capability_registry.py
agentic_kernel/communication/error_handler.py
agentic_kernel/communication/feedback.py
agentic_kernel/communication/message.py
agentic_kernel/communication/protocol.py
agentic_kernel/communication/trust.py
agentic_kernel/communication/a2a/README.md
agentic_kernel/communication/a2a/__init__.py
agentic_kernel/communication/a2a/client.py
agentic_kernel/communication/a2a/jsonrpc.py
agentic_kernel/communication/a2a/server.py
agentic_kernel/communication/a2a/simple_server.py
agentic_kernel/communication/a2a/task.py
agentic_kernel/communication/a2a/types.py
agentic_kernel/communication/a2a/examples/__init__.py
agentic_kernel/communication/a2a/examples/simple_example.py
agentic_kernel-0.2.10.dist-info/METADATA
agentic_kernel-0.2.10.dist-info/WHEEL
agentic_kernel-0.2.10.dist-info/licenses/CHANGELOG.md
agentic_kernel-0.2.10.dist-info/licenses/LICENSE
agentic_kernel-0.2.10.dist-info/RECORD
