Metadata-Version: 2.4
Name: agentic-kernel
Version: 0.2.10
Summary: A Python library for building agentic applications
Project-URL: Homepage, https://github.com/qredence/agentic-kernel
Project-URL: Documentation, https://github.com/qredence/agentic-kernel/docs
Project-URL: Repository, https://github.com/qredence/agentic-kernel.git
Project-URL: Bug Tracker, https://github.com/qredence/agentic-kernel/issues
Project-URL: Changelog, https://github.com/qredence/agentic-kernel/blob/main/CHANGELOG.md
Author-email: "Qredence.ai" <contact@qredence.ai>
License-Expression: MIT
License-File: CHANGELOG.md
License-File: LICENSE
Keywords: agents,ai,automation,langchain,openai,semantic-kernel
Classifier: Development Status :: 4 - Beta
Classifier: Intended Audience :: Developers
Classifier: License :: OSI Approved :: MIT License
Classifier: Operating System :: OS Independent
Classifier: Programming Language :: Python :: 3
Classifier: Programming Language :: Python :: 3.10
Classifier: Programming Language :: Python :: 3.11
Classifier: Programming Language :: Python :: 3.12
Classifier: Programming Language :: Python :: 3.13
Classifier: Topic :: Scientific/Engineering :: Artificial Intelligence
Classifier: Topic :: Software Development :: Libraries :: Python Modules
Requires-Python: <3.14,>=3.10
Requires-Dist: aiohttp<4.0.0,>=3.11.14
Requires-Dist: asyncio<4.0.0,>=3.4.3
Requires-Dist: asyncpg<1.0.0,>=0.29.0
Requires-Dist: azure-ai-documentintelligence<1.1.0,>=1.0.2
Requires-Dist: azure-ai-evaluation<1.6.0,>=1.5.0
Requires-Dist: azure-ai-inference<2.0.0,>=1.0.0b1
Requires-Dist: azure-ai-projects<2.0.0,>=1.0.0b6
Requires-Dist: azure-core<2.0.0,>=1.30.1
Requires-Dist: azure-identity<2.0.0,>=1.15.0
Requires-Dist: azure-search-documents<12.0.0,>=11.6.0b10
Requires-Dist: azure-storage-blob<13.0.0,>=12.19.0
Requires-Dist: beautifulsoup4<4.14.0,>=4.13.3
Requires-Dist: chainlit<3.0.0,>=2.4.400
Requires-Dist: fastapi<0.116.0,>=0.115.12
Requires-Dist: google-adk<0.2.0,>=0.1.1
Requires-Dist: httpx<0.29.0,>=0.28.1
Requires-Dist: langchain<1.0.0,>=0.0.309
Requires-Dist: markitdown<0.2.0,>=0.1.1
Requires-Dist: matplotlib<3.11.0,>=3.10.1
Requires-Dist: mem0ai<0.2.0,>=0.1.90
Requires-Dist: networkx<3.5.0,>=3.4.2
Requires-Dist: openai<1.73.0,>=1.72.0
Requires-Dist: playwright<2.0.0,>=1.51.0
Requires-Dist: psutil<6.0.0,>=5.9.5
Requires-Dist: pyautogui<1.0.0,>=0.9.54
Requires-Dist: pydantic<3.0.0,>=2.6.3
Requires-Dist: pydot<3.1.0,>=3.0.4
Requires-Dist: python-dotenv<1.2.0,>=1.1.0
Requires-Dist: requests<3.0.0,>=2.31.0
Requires-Dist: rich<15.0.0,>=14.0.0
Requires-Dist: ruff<1.0.0,>=0.11.4
Requires-Dist: semantic-kernel<1.29.0,>=1.28.0
Requires-Dist: starlette<0.42.0,>=0.41.3
Requires-Dist: tabulate<0.10.0,>=0.9.0
Requires-Dist: typer[all]<1.0.0,>=0.15.2
Provides-Extra: dev
Requires-Dist: black<25.0.0,>=24.10.0; extra == 'dev'
Requires-Dist: coverage[toml]<8.0.0,>=7.4.0; extra == 'dev'
Requires-Dist: isort<6.0.0,>=5.13.2; extra == 'dev'
Requires-Dist: mypy<2.0.0,>=1.15.0; extra == 'dev'
Requires-Dist: pylint<4.0.0,>=3.1.0; extra == 'dev'
Requires-Dist: pytest-asyncio<0.27.0,>=0.26.0; extra == 'dev'
Requires-Dist: pytest<9.0.0,>=8.3.5; extra == 'dev'
Requires-Dist: responses<1.0.0,>=0.25.0; extra == 'dev'
Requires-Dist: ruff<1.0.0,>=0.11.4; extra == 'dev'
Requires-Dist: sphinx-rtd-theme<1.4.0,>=1.3.0; extra == 'dev'
Requires-Dist: sphinx<8.0.0,>=7.0.0; extra == 'dev'
Requires-Dist: types-requests<3.0.0,>=2.31.0; extra == 'dev'
Requires-Dist: types-tabulate<0.10.0,>=0.9.0; extra == 'dev'
